hbin/__init__.py
hbin/cli.py
hbin-0.1.0.dist-info/METADATA
hbin-0.1.0.dist-info/WHEEL
hbin-0.1.0.dist-info/entry_points.txt
hbin-0.1.0.dist-info/top_level.txt
hbin-0.1.0.dist-info/RECORD
