Metadata-Version: 2.4
Name: hbin
Version: 0.1.0
Summary: Save Bash history as snippets / history tooling
Author: LM Web Tech.
Requires-Python: >=3.9
